Metadata-Version: 1.0
Name: squ
Version: 0.0.2
Summary: self-used utils
Home-page: https://github.com/Squirre17/python-utils
Author: Ler2sq
Author-email: ler2sq@gmail.com
License: UNKNOWN
Platform: UNKNOWN
